{
  "id": "a044973",
  "title": "ネコ　ノ　オバアサン",
  "author": "村山籌子",
  "metadata": {
    "publicationYear": 1900,
    "genre": [
      "文学"
    ],
    "estimatedReadTime": 30,
    "difficulty": 2,
    "pages": 3
  },
  "structure": {
    "chapters": [
      {
        "id": "chapter-1",
        "title": "ネコ　ノ　オバアサン",
        "startPage": 1,
        "endPage": 3,
        "summary": "ねこのおばあさんの物語"
      }
    ],
    "totalPages": 3,
    "averageCharsPerPage": 377,
    "chapterTitles": []
  },
  "content": [
    {
      "pageNumber": 1,
      "content": "ネコ　ノ　オバアサン",
      "characters": 10,
      "ruby": [],
      "displayType": "book-title"
    },
    {
      "pageNumber": 2,
      "content": "　タイヘントシトツタオバアサンネコガ、オヒルコロニナツテメヲサマシテ、ベツドノウヘヘオキアガリマシタ。オバアサンハ、セイヨウネコデシタカラ、ナイト・キヤツプトイフヅキンヲカブツテ、ナイト・ガウントイフネマキヲキテ、メガネヲカケテヰマス。「アア、チツトモ、オチツイテネムレナカツタ。イマイマシイ。ナンダカサムクツテシカタガナイカラ、コノナカデ、ホンヲヨミマセウ。」ト、ヨツピテグツスリネコンダノニ、マダネタイデスガ、メガサメテシマツテネムレナイノデ、ホンヲヒロゲテヨミマセウトシマストキウニ、マドノスグソトデ、パタパタトハシリマハルオトガシマシタ。「オヤ、ナンダロ。」ト、オバアサンハプリプリシテ、マドノソトヲミマシタラ、キンジヨノミケ子トトラ三ガ、ランニングヲシテヰマシタ。「ヤカマシイコトバカリシテ。ワタシガ、ヨクネムレナカツタノヲシラナイノカ。ホントニ、ヨノナカハヒトノキヲシランヤツガオホクテコマル。」トヒトリデ、ブツブツオコリナガラ、マタホンヲヨミハジメマシタ。",
      "characters": 435,
      "ruby": []
    },
    {
      "pageNumber": 3,
      "content": "　オバアサンガ一字ヨムカヨマナイウチニ――オバアサンハ、ムツカシイ字ヲヨムトキハ一字ヨムノニトテモ時間ガカカルノデス――マドノソトデ、ハリサケルヤウナオホキナオトガ、キコエマシタ。ソシテ「ソラ、タマガトンダヨ。トツテキテ、ハヤクナゲルンダヨ――」ト、トラ三ガドナツテヰタノデ、オバアサンハビツクリシマシタ。「コリヤイカン。サツキヨリ、マダヤカマシクナツタ。ヤキユウヲシテルンダナ。ヤキユウヲスルノニ、ダマツテデキナイナンテ、ナンテ、バカナ小僧タチダ。」オバアサンハ、ベツドノウヘデオコツテヰマシタガ、「モウシカタガナイ。ココヂヤアネムレナイ。アサゴハンデモタベルトシヨウ。」トプリプリシテ、オダイドコロヘオリテユキマシタガ、マダ、オシタクガデキテヰマセン。オバアサンハ、マスマスオコリマシタガ、シカタガナイノデ、オザシキノアンラクヰスニコシヲカケマシタラ、タウトウキモチガヨクナツテ、マユヲシカメタママネムリコンデシマヒマシタ。\n\n　ユウガタニナリマシタ。「ナンテ、オモシロカツタンダラウ。アシタマタアソバウヨ。」ト、ミミガヤブケルヤウナオホキナコエヲシテ、ミケ子トトラ三ガ、マドノソトヲトホツテユキマシタラ、オバアサンハヤツトメヲサマシマシタ。オバアサンハハラガタツテシカタガアリマセン。「ヤキユウヲスルノニ、コエヲダサナイデスルトイフワケニハユカンモンデスカネ。」ト、アフヒトゴトニオコリマシタ。\n\n　ネコノオバアサンハ、マイニチ、コンナフウニクラシテヰマス。ケレドモ、オバアサンハヨイネコデスカラ、ケツシテコドモガドンナニヤカマシクシテモ、ドナリツケタリハイタシマセン。",
      "characters": 688,
      "ruby": []
    }
  ]
}