{
  "id": "a053707",
  "title": "線に関する覚書７",
  "author": "李箱",
  "metadata": {
    "publicationYear": 1900,
    "genre": [
      "文学"
    ],
    "estimatedReadTime": 30,
    "difficulty": 2,
    "pages": 3
  },
  "structure": {
    "chapters": [
      {
        "id": "chapter-1",
        "title": "線に関する覚書７",
        "startPage": 1,
        "endPage": 3
      }
    ],
    "totalPages": 3,
    "averageCharsPerPage": 184,
    "chapterTitles": []
  },
  "content": [
    {
      "pageNumber": 1,
      "content": "線に関する覚書７",
      "characters": 8,
      "ruby": [],
      "displayType": "book-title"
    },
    {
      "pageNumber": 2,
      "content": "　空気構造の速度―音波に依る―速度らしく三百三十メートルを模倣する（何んと光に比しての甚だしき劣り方だらう）\n\n　光を楽めよ、光を悲しめよ、光を笑へよ、光を泣けよ。\n\n　光が人であると人は鏡である。\n\n　光を持てよ。\n\n　――\n\n　視覚のナマエを持つことは計画の嚆矢である。視覚のナマエを発表せよ。\n\n□　オレノの《ママ》ナマエ。\n\n△　オレの妻のナマエ（既に古い過去においてオレの AMOUREUSE は斯くの如く聡明である）\n\n　視覚のナマエの通路は設けよ、そしてそれに最大の速度を与へよ。",
      "characters": 247,
      "ruby": []
    },
    {
      "pageNumber": 3,
      "content": "　――\n\n　ソラは視覚のナマエについてのみ存在を明かにする（代表のオレは代表の一例を挙げること）\n\n　蒼空、秋天、蒼天、青天、長天、一天、蒼穹（非常に窮屈な地方色ではなからうか）ソラは視覚のナマエを発表した。\n\n　視覚のナマエは人と共に永遠に生きるべき数字的である或る一点である、視覚のナマエは運動しないで運動のコヲスを持つばかりである。\n\n　――\n\n　視覚のナマエは光を持つ光を持たない、人は視覚のナマエのために光よりも迅く逃げる必要はない。\n\n　視覚のナマエらを健忘せよ。\n\n　視覚のナマエを節約せよ。\n\n　人は光よりも迅く逃げる速度を調節し度々過去を未来において淘汰せよ。一九三一、九、一二",
      "characters": 298,
      "ruby": []
    }
  ]
}