{
  "id": "a061342",
  "title": "メランコリア",
  "author": "三富朽葉",
  "metadata": {
    "publicationYear": 1900,
    "genre": [
      "文学"
    ],
    "estimatedReadTime": 30,
    "difficulty": 2,
    "pages": 6
  },
  "structure": {
    "chapters": [
      {
        "id": "chapter-1",
        "title": "メランコリア",
        "startPage": 1,
        "endPage": 6
      }
    ],
    "totalPages": 6,
    "averageCharsPerPage": 154,
    "chapterTitles": [
      "メランコリア"
    ]
  },
  "content": [
    {
      "pageNumber": 1,
      "content": "メランコリア",
      "characters": 6,
      "ruby": [],
      "displayType": "book-title"
    },
    {
      "pageNumber": 2,
      "content": "　外から砂鐵《さてつ》の臭《にほひ》を持つて來る海際の午後、\n\n象《ざう》の戯《たはむ》れるやうな濤《なみ》の呻吟《うなり》は\n\n壘の上に横たへる身體《からだ》を\n\n分解《ぶんかい》しやうと揉《も》んでまわる。\n\n私は或日珍らしくも無い原素《げんそ》に成つて\n\n重《おも》いメランコリイの底《そこ》へ沈《しつ》んで了ふであらう。\n\nえたひの知れぬ此ひと時の衰へよ、\n\n身動《みうご》きも出來ない痺《しび》れが\n\n筋肉《きんにく》のあたりを延びて行く…………",
      "characters": 228,
      "ruby": []
    },
    {
      "pageNumber": 3,
      "content": "限りない物思ひのあるような、空しさ。\n\n鑠《や》ける光線《くわうせん》に續《つな》がれて\n\n目まぐるしい蠅《はい》のひと群《むれ》が旋《めぐ》る。\n\n私は或日、砂地《すなぢ》の影《かげ》へ身を潜《ひそ》めて\n\n水月《くらげ》のやうに音《おと》もなく溶《と》け入《い》るであらう。\n\n太陽は紅《あか》い、紅いイリユージヨンを夢みてゐる、\n\n私は不思議な役割をつとめてるのでは無いか。\n\n無花果樹《いちじく》の蔭の籐椅子《とゐす》や、\n\nまいまいつむりの脆《もろ》い殼《から》の邊《あたり》へ",
      "characters": 244,
      "ruby": []
    },
    {
      "pageNumber": 4,
      "content": "私は蠅の群となつて舞ひに行く、\n\n壁《かべ》の廻《まは》りの紛《まぎ》れ易い模樣にも\n\n一寸臂《しり》を突《つ》き出して止つて見た。\n\n窓《まど》の下《した》に死にゆくやうな尨犬《むくいぬ》よ。\n\n私は何時《いつ》しかその上で渦卷《うづま》き初める、\n\n…………………………\n\n…………………………\n\n砂鐵の臭の懶《ものう》いひとすぢ。（八月）\n\n　　　　○",
      "characters": 179,
      "ruby": []
    },
    {
      "pageNumber": 5,
      "content": "午後の薄明《うすあか》りの中で、\n\n奇妙《きめう》な睡《ねむ》りに落ちて行く\n\n影を曳《ひ》く安樂椅子《あんらくゐす》の\n\n病の身を搖る儘に。\n\n懶《ものう》げな雨の線條《すぢ》は\n\n音も無く若葉の匂を煙らす\n\n姿《すがた》を見せぬ鳥の囀《さへづ》りの\n\n壞《くづ》れた胸に響くことよ！\n\n永い間の疲勞《つかれ》が",
      "characters": 157,
      "ruby": []
    },
    {
      "pageNumber": 6,
      "content": "重く夢を壓《お》す時に\n\n鳥は青い叫《さけ》びを殘《のこ》して翔《かけ》る。\n\n春は微笑んでゐるのかも知れないけれど\n\n欝《くら》い蔭《かげ》を搖る安樂椅子の\n\nさけ難《がた》い睡《ねむ》りに包《つゝ》まれる…………\n\n（四月）",
      "characters": 114,
      "ruby": []
    }
  ]
}