{
  "id": "a045033",
  "title": "港の唄",
  "author": "山村暮鳥",
  "metadata": {
    "publicationYear": 1900,
    "genre": [
      "文学"
    ],
    "estimatedReadTime": 30,
    "difficulty": 2,
    "pages": 3
  },
  "structure": {
    "chapters": [
      {
        "id": "chapter-1",
        "title": "港の唄",
        "startPage": 1,
        "endPage": 1
      }
    ],
    "totalPages": 3,
    "averageCharsPerPage": 37,
    "chapterTitles": []
  },
  "content": [
    {
      "pageNumber": 1,
      "content": "港の唄",
      "characters": 3,
      "ruby": [],
      "displayType": "book-title"
    },
    {
      "pageNumber": 2,
      "content": "みなとの\n\nはるのよ\n\nあめもよひ\n\nどこから\n\nきたのか\n\nふながかり\n\nみなとの\n\nてんまに\n\nひがついた",
      "characters": 55,
      "ruby": []
    },
    {
      "pageNumber": 3,
      "content": "ひとつ\n\nぽつちり\n\nひがついた\n\nみなとの\n\nはるのよ\n\nあめもよひ\n\nてんまで\n\nあかごが\n\nないてゐた",
      "characters": 54,
      "ruby": []
    }
  ]
}