{
  "id": "a055225",
  "title": "びるぜん祈祷",
  "author": "ダンテアリギエリ",
  "metadata": {
    "publicationYear": 1900,
    "genre": [
      "文学"
    ],
    "estimatedReadTime": 30,
    "difficulty": 2,
    "pages": 6
  },
  "structure": {
    "chapters": [
      {
        "id": "chapter-1",
        "title": "びるぜん祈祷",
        "startPage": 1,
        "endPage": 1
      }
    ],
    "totalPages": 6,
    "averageCharsPerPage": 106,
    "chapterTitles": []
  },
  "content": [
    {
      "pageNumber": 1,
      "content": "びるぜん祈祷",
      "characters": 6,
      "ruby": [],
      "displayType": "book-title"
    },
    {
      "pageNumber": 2,
      "content": "母なるをとめ、わが子のむすめ、\n\n賤しくして、また、なによりも尊く、\n\n永遠の謀のさだかなるめあて、\n\n君こそは人性を尊からしむれ、\n\n物みなの造りぬしも、\n\n其造りなるを卑まざりき。\n\nその胎に照りたる愛は、\n\nこの花をとこ世に靜けく、\n\n温め生ふし開き給ひぬ。",
      "characters": 132,
      "ruby": []
    },
    {
      "pageNumber": 3,
      "content": "ここにゐては愛の央《なかば》の松あかし。\n\n下界人間に雜《まじ》はりては、望の生ける泉なり。\n\n大なる哉、徳ある哉、われらの君よ、\n\n恩寵《めぐみ》をえまくほりする者、\n\n君の御前にまだ來ぬは、\n\nその願ひ翼なくして飛ぶを思ふや。\n\n御慈悲《いつくしみ》は、願ひ人を助くるのみならず、\n\nおのづから願に先だつこと多かり。\n\n君に憐、君に悲、君に惠、",
      "characters": 174,
      "ruby": []
    },
    {
      "pageNumber": 4,
      "content": "造化のよしといふよき物は君に集《つど》ひぬ。\n\n茲に今、宇宙の池のいと深き底より、\n\nこの天堂にしも、また昇り、\n\n靈のひとつびとつを眺むるもの、\n\n伏して願はくは、終の福《さいはひ》にむかひ、\n\n眼《まなこ》うち仰ぎ得むことを祈る。\n\n今彼の眺を望むばかり、\n\n己が眺を望む時にも切ならざりし吾。\n\n茲に一切の祈を捧げて、",
      "characters": 162,
      "ruby": []
    },
    {
      "pageNumber": 5,
      "content": "足らざること勿れと念ず。\n\n君よ、人間の迷雲を此人より拂ひて、\n\n至上の悦をえさせたまへ。\n\n重ねて祈り申さく\n\n思のまゝのなべてを行ふ后《きさい》の宮よ、\n\nかゝる大觀の後までも、\n\nかれが心をそこなはず、\n\n君の護のあるが故に、\n\n人間の混亂を滅ぼし給へ。",
      "characters": 130,
      "ruby": []
    },
    {
      "pageNumber": 6,
      "content": "わが祈に添ひてベアトリチエと諸聖と、\n\n合掌祈念するをも、うけさせ給へや。",
      "characters": 37,
      "ruby": []
    }
  ]
}